cRegression/__init__.py
cRegression/cRegression.cp311-win_amd64.pyd
cregression-0.1.0.dist-info/METADATA
cregression-0.1.0.dist-info/WHEEL
cregression-0.1.0.dist-info/licenses/LICENSE
cregression-0.1.0.dist-info/RECORD
