Metadata-Version: 2.2
Name: cRegression
Version: 0.1.0
Summary: Fast C++ regression library with Python bindings
Author: Awais
License: MIT License
Classifier: Programming Language :: Python :: 3
Classifier: Programming Language :: C++
Classifier: Operating System :: OS Independent
Requires-Python: >=3.8
Requires-Dist: numpy
